MANIFEST.in
README.rst
VERSION
setup.cfg
setup.py
etc/nginx.conf.template
sagemaker_containers.egg-info/PKG-INFO
sagemaker_containers.egg-info/SOURCES.txt
sagemaker_containers.egg-info/dependency_links.txt
sagemaker_containers.egg-info/entry_points.txt
sagemaker_containers.egg-info/requires.txt
sagemaker_containers.egg-info/top_level.txt
src/sagemaker_containers/__init__.py
src/sagemaker_containers/_content_types.py
src/sagemaker_containers/_encoders.py
src/sagemaker_containers/_entry_point_type.py
src/sagemaker_containers/_env.py
src/sagemaker_containers/_errors.py
src/sagemaker_containers/_files.py
src/sagemaker_containers/_functions.py
src/sagemaker_containers/_intermediate_output.py
src/sagemaker_containers/_logging.py
src/sagemaker_containers/_mapping.py
src/sagemaker_containers/_modules.py
src/sagemaker_containers/_mpi.py
src/sagemaker_containers/_params.py
src/sagemaker_containers/_process.py
src/sagemaker_containers/_recordio.py
src/sagemaker_containers/_runner.py
src/sagemaker_containers/_server.py
src/sagemaker_containers/_timeout.py
src/sagemaker_containers/_trainer.py
src/sagemaker_containers/_transformer.py
src/sagemaker_containers/_worker.py
src/sagemaker_containers/entry_point.py
src/sagemaker_containers/record_pb2.py
src/sagemaker_containers/beta/__init__.py
src/sagemaker_containers/beta/framework/__init__.py
src/sagemaker_containers/c/gethostname.c
src/sagemaker_containers/c/jsmn.c
src/sagemaker_containers/c/jsmn.h
src/sagemaker_containers/cli/__init__.py
src/sagemaker_containers/cli/serve.py
src/sagemaker_containers/cli/train.py